py_random_useragent/__init__.py
py_random_useragent/__main__.py
py_random_useragent/main.py
py_random_useragent/user_agent.py
py_random_useragent-0.2.0.dist-info/METADATA
py_random_useragent-0.2.0.dist-info/WHEEL
py_random_useragent-0.2.0.dist-info/entry_points.txt
py_random_useragent-0.2.0.dist-info/RECORD
